{
  "button": {
    "primary": {
      "border": {
        "value": {
          "color": "{button.primary.border-color}",
          "width": "{dimen-10}",
          "style": "solid"
        },
        "type": "border"
      }
    },
    "negative": {
      "border": {
        "value": {
          "width": "{dimen-10}",
          "color": "{button.negative.border-color}",
          "style": "solid"
        },
        "type": "border"
      }
    },
    "outline": {
      "border": {
        "value": {
          "color": "{button.outline.border-color}",
          "width": "{dimen-10}",
          "style": "solid"
        },
        "type": "border"
      }
    },
    "border-radius": {
      "value": "{border-radius-120}",
      "type": "borderRadius"
    },
    "spacing": {
      "horizontal": {
        "value": "{dimen-120}",
        "type": "spacing"
      },
      "vertical": {
        "value": "{dimen-80}",
        "type": "spacing"
      }
    }
  }
}